timepro_timesheet/__init__.py
timepro_timesheet/api.py
timepro_timesheet/cli.py
timepro_timesheet/timesheet.py
timepro_timesheet/utils.py
timepro_timesheet/version.py
timepro_timesheet-19.2.1.dist-info/LICENSE
timepro_timesheet-19.2.1.dist-info/METADATA
timepro_timesheet-19.2.1.dist-info/WHEEL
timepro_timesheet-19.2.1.dist-info/entry_points.txt
timepro_timesheet-19.2.1.dist-info/top_level.txt
timepro_timesheet-19.2.1.dist-info/RECORD
