Metadata-Version: 2.1
Name: timepro-timesheet
Version: 19.2.1
Summary: Utility for programmatically getting and submitting data to Intertec TimePro (timesheets.com.au)
Home-page: http://github.com/christippett/timepro-timesheet
Author: Chris Tippett
Author-email: c.tippett@gmail.com
License: MIT
Platform: UNKNOWN
Classifier: Environment :: Web Environment
Classifier: Operating System :: OS Independent
Classifier: License :: OSI Approved :: MIT License
Classifier: Programming Language :: Python
Classifier: Programming Language :: Python :: 3.6
Classifier: Programming Language :: Python :: 3.7
Requires-Dist: requests
Requires-Dist: requests-html
Requires-Dist: python-dateutil
